energy_es/__init__.py
energy_es/__main__.py
energy_es/env.py
energy_es/data/__init__.py
energy_es/data/prices.py
energy_es/ui/__init__.py
energy_es/ui/about_dialog.py
energy_es/ui/chart.py
energy_es/ui/main_window.py
energy_es/ui/workers.py
energy_es/ui/images/logo.png
energy_es-0.1.0.dist-info/LICENSE
energy_es-0.1.0.dist-info/METADATA
energy_es-0.1.0.dist-info/WHEEL
energy_es-0.1.0.dist-info/entry_points.txt
energy_es-0.1.0.dist-info/top_level.txt
energy_es-0.1.0.dist-info/RECORD
