Metadata-Version: 2.1
Name: energy-es
Version: 0.1.0
Summary: Desktop application that shows an interactive chart with the hourly values of the Spot Market and PVPC energy prices of the current day in Spain.
Home-page: https://github.com/jajimenez/energy-es
Author: Jose A. Jimenez
Author-email: jajimenezcarm@gmail.com
License: MIT
Platform: UNKNOWN
Classifier: Programming Language :: Python :: 3
Classifier: Operating System :: OS Independent
Classifier: License :: OSI Approved :: MIT License
Requires-Python: >=3.9.0
Requires-Dist: requests (==2.28.1)
Requires-Dist: pyside6 (==6.4.1)
Requires-Dist: pandas (==1.5.2)
Requires-Dist: plotly (==5.11.0)
Requires-Dist: userconf (==0.5.0)
